LICENSE.txt
MANIFEST.in
README.md
requirements.txt
setup.py
threatresponse/__init__.py
threatresponse/client.py
threatresponse/exceptions.py
threatresponse/urls.py
threatresponse/version.py
threatresponse.egg-info/PKG-INFO
threatresponse.egg-info/SOURCES.txt
threatresponse.egg-info/dependency_links.txt
threatresponse.egg-info/requires.txt
threatresponse.egg-info/top_level.txt
threatresponse/api/__init__.py
threatresponse/api/asset.py
threatresponse/api/base.py
threatresponse/api/bundle.py
threatresponse/api/casebook.py
threatresponse/api/commands.py
threatresponse/api/enrich.py
threatresponse/api/entity.py
threatresponse/api/event.py
threatresponse/api/feed.py
threatresponse/api/incident.py
threatresponse/api/indicator.py
threatresponse/api/inspect.py
threatresponse/api/int.py
threatresponse/api/intel.py
threatresponse/api/judgement.py
threatresponse/api/module_type_patch.py
threatresponse/api/profile.py
threatresponse/api/response.py
threatresponse/api/sighting.py
threatresponse/api/sse.py
threatresponse/api/user_mgmt.py
threatresponse/api/vulnerability.py
threatresponse/api/routing/__init__.py
threatresponse/api/routing/resolution.py
threatresponse/api/routing/router.py
threatresponse/request/__init__.py
threatresponse/request/authorized.py
threatresponse/request/base.py
threatresponse/request/logged.py
threatresponse/request/proxied.py
threatresponse/request/relative.py
threatresponse/request/response.py
threatresponse/request/standard.py
threatresponse/request/timed.py