Metadata-Version: 2.1
Name: threatresponse
Version: 0.15.0
Summary: Threat Response API Module
Home-page: https://github.com/CiscoSecurity/tr-05-api-module
Author: Cisco Security
License: MIT
Keywords: cisco,security,threat,response,api,module,python
Platform: UNKNOWN
Classifier: Intended Audience :: Developers
Classifier: Operating System :: OS Independent
Classifier: Programming Language :: Python
Classifier: Programming Language :: Python :: 2
Classifier: Programming Language :: Python :: 2.6
Classifier: Programming Language :: Python :: 2.7
Classifier: Programming Language :: Python :: 3
Classifier: Programming Language :: Python :: 3.5
Classifier: Programming Language :: Python :: 3.6
Classifier: Programming Language :: Python :: 3.7
Classifier: Programming Language :: Python :: 3.8
Classifier: Topic :: Software Development :: Libraries :: Python Modules
Requires-Python: >=2.6
License-File: LICENSE.txt
